{
	"archive" : {},
	"artifacts" : 
	[
		{
			"path" : "serial/libserial.a"
		}
	],
	"backtrace" : 1,
	"backtraceGraph" : 
	{
		"commands" : 
		[
			"add_library",
			"include_directories",
			"target_link_libraries"
		],
		"files" : 
		[
			"serial/CMakeLists.txt",
			"CMakeLists.txt"
		],
		"nodes" : 
		[
			{
				"file" : 0
			},
			{
				"command" : 0,
				"file" : 0,
				"line" : 6,
				"parent" : 0
			},
			{
				"file" : 1
			},
			{
				"command" : 1,
				"file" : 1,
				"line" : 8,
				"parent" : 2
			},
			{
				"command" : 1,
				"file" : 1,
				"line" : 9,
				"parent" : 2
			},
			{
				"command" : 2,
				"file" : 0,
				"line" : 7,
				"parent" : 0
			}
		]
	},
	"compileGroups" : 
	[
		{
			"compileCommandFragments" : 
			[
				{
					"fragment" : "-g -fdiagnostics-color=always"
				},
				{
					"fragment" : "-std=gnu++14"
				}
			],
			"includes" : 
			[
				{
					"backtrace" : 3,
					"path" : "/usr/local/include/opencv4"
				},
				{
					"backtrace" : 4,
					"path" : "/home/quonone/workspace/Armor_project/include"
				}
			],
			"language" : "CXX",
			"languageStandard" : 
			{
				"backtraces" : 
				[
					5
				],
				"standard" : "14"
			},
			"sourceIndexes" : 
			[
				0
			]
		}
	],
	"id" : "serial::@f50a2cc8b0e9321cdd57",
	"name" : "serial",
	"nameOnDisk" : "libserial.a",
	"paths" : 
	{
		"build" : "serial",
		"source" : "serial"
	},
	"sourceGroups" : 
	[
		{
			"name" : "Source Files",
			"sourceIndexes" : 
			[
				0
			]
		}
	],
	"sources" : 
	[
		{
			"backtrace" : 1,
			"compileGroupIndex" : 0,
			"path" : "serial/serial.cpp",
			"sourceGroupIndex" : 0
		}
	],
	"type" : "STATIC_LIBRARY"
}
